ckanext/__init__.py
ckanext/editable_config/__init__.py
ckanext/editable_config/config.py
ckanext/editable_config/config_declaration.yaml
ckanext/editable_config/helpers.py
ckanext/editable_config/plugin.py
ckanext/editable_config/shared.py
ckanext/editable_config/views.py
ckanext/editable_config/assets/webassets.yml
ckanext/editable_config/assets/css/editable_config.css
ckanext/editable_config/assets/js/editable-config-toggle-field.js
ckanext/editable_config/logic/__init__.py
ckanext/editable_config/logic/action.py
ckanext/editable_config/logic/auth.py
ckanext/editable_config/logic/schema.py
ckanext/editable_config/logic/validators.py
ckanext/editable_config/migration/editable_config/alembic.ini
ckanext/editable_config/migration/editable_config/env.py
ckanext/editable_config/migration/editable_config/script.py.mako
ckanext/editable_config/migration/editable_config/versions/a8d116986c3f_create_editable_config_table.py
ckanext/editable_config/model/__init__.py
ckanext/editable_config/model/option.py
ckanext/editable_config/templates/admin/base.html
ckanext/editable_config/templates/editable_config/config.html
ckanext/editable_config/templates/editable_config/snippets/field.html
ckanext/editable_config/tests/__init__.py
ckanext/editable_config/tests/conftest.py
ckanext/editable_config/tests/test_fixtures.py
ckanext/editable_config/tests/test_plugin.py
ckanext/editable_config/tests/test_shared.py
ckanext/editable_config/tests/logic/__init__.py
ckanext/editable_config/tests/logic/test_action.py
ckanext/editable_config/tests/logic/test_schema.py
ckanext/editable_config/tests/model/__init__.py
ckanext/editable_config/tests/model/test_option.py
ckanext_editable_config-0.0.8.dist-info/LICENSE
ckanext_editable_config-0.0.8.dist-info/METADATA
ckanext_editable_config-0.0.8.dist-info/WHEEL
ckanext_editable_config-0.0.8.dist-info/entry_points.txt
ckanext_editable_config-0.0.8.dist-info/top_level.txt
ckanext_editable_config-0.0.8.dist-info/RECORD
