Metadata-Version: 2.1
Name: ckanext-editable-config
Version: 0.0.8
Author-email: DataShades <datashades@linkdigital.com.au>, Sergey Motornyuk <sergey.motornyuk@linkdigital.com.au>
Maintainer-email: DataShades <datashades@linkdigital.com.au>
License: AGPL
Project-URL: Homepage, https://github.com/ckan/ckanext-editable-config
Keywords: CKAN
Classifier: Development Status :: 4 - Beta
Classifier: License :: OSI Approved :: GNU Affero General Public License v3 or later (AGPLv3+)
Classifier: Programming Language :: Python :: 3.8
Classifier: Programming Language :: Python :: 3.9
Classifier: Programming Language :: Python :: 3.10
License-File: LICENSE
Provides-Extra: dev
Requires-Dist: pytest-ckan ; extra == 'dev'
Requires-Dist: git-changelog ; extra == 'dev'
Provides-Extra: test
Requires-Dist: pytest-ckan ; extra == 'test'
